[{"name":"Auto Drink","type":"AUTO_DRINK","faction":"your_followers","invert":false,"enabled":true,"is_vehicle":false,"is_personal":false,"cached_shift":[0,0,0],"start":[3387,3365,0],"end":[3387,3365,0]},{"name":"","type":"NPC_INVESTIGATE_ONLY","faction":"no_faction","invert":false,"enabled":true,"is_vehicle":false,"is_personal":false,"cached_shift":[0,0,0],"start":[3293,3051,0],"end":[3297,3062,0]},{"name":"","type":"NPC_INVESTIGATE_ONLY","faction":"no_faction","invert":false,"enabled":true,"is_vehicle":false,"is_personal":false,"cached_shift":[0,0,0],"start":[3269,2979,0],"end":[3273,2990,0]},{"name":"","type":"NPC_INVESTIGATE_ONLY","faction":"no_faction","invert":false,"enabled":true,"is_vehicle":false,"is_personal":false,"cached_shift":[0,0,0],"start":[3278,3081,0],"end":[3282,3092,0]},{"name":"","type":"NPC_INVESTIGATE_ONLY","faction":"no_faction","invert":false,"enabled":true,"is_vehicle":false,"is_personal":false,"cached_shift":[0,0,0],"start":[3245,3051,0],"end":[3249,3062,0]},{"name":"","type":"NPC_INVESTIGATE_ONLY","faction":"no_faction","invert":false,"enabled":true,"is_vehicle":false,"is_personal":false,"cached_shift":[0,0,0],"start":[2908,3291,0],"end":[2920,3293,0]},{"name":"","type":"NPC_INVESTIGATE_ONLY","faction":"free_merchants","invert":false,"enabled":true,"is_vehicle":false,"is_personal":false,"cached_shift":[0,0,0],"start":[3960,3312,0],"end":[3983,3335,0]},{"name":"","type":"NPC_INVESTIGATE_ONLY","faction":"wasteland_scavengers","invert":false,"enabled":true,"is_vehicle":false,"is_personal":false,"cached_shift":[0,0,0],"start":[3960,3312,0],"end":[3983,3335,0]},{"name":"","type":"NPC_INVESTIGATE_ONLY","faction":"old_guard","invert":false,"enabled":true,"is_vehicle":false,"is_personal":false,"cached_shift":[0,0,0],"start":[3964,3317,0],"end":[3981,3335,0]},{"name":"","type":"NPC_INVESTIGATE_ONLY","faction":"free_merchants","invert":false,"enabled":true,"is_vehicle":false,"is_personal":false,"cached_shift":[0,0,0],"start":[3960,3336,0],"end":[3983,3359,0]},{"name":"","type":"NPC_INVESTIGATE_ONLY","faction":"wasteland_scavengers","invert":false,"enabled":true,"is_vehicle":false,"is_personal":false,"cached_shift":[0,0,0],"start":[3960,3336,0],"end":[3983,3359,0]},{"name":"","type":"NPC_INVESTIGATE_ONLY","faction":"old_guard","invert":false,"enabled":true,"is_vehicle":false,"is_personal":false,"cached_shift":[0,0,0],"start":[3964,3336,0],"end":[3981,3347,0]},{"name":"","type":"NPC_INVESTIGATE_ONLY","faction":"old_guard","invert":false,"enabled":true,"is_vehicle":false,"is_personal":false,"cached_shift":[0,0,0],"start":[3983,3336,0],"end":[3983,3336,0]},{"name":"","type":"NPC_INVESTIGATE_ONLY","faction":"lobby_beggars","invert":false,"enabled":true,"is_vehicle":false,"is_personal":false,"cached_shift":[0,0,0],"start":[3979,3339,0],"end":[3983,3356,0]},{"name":"","type":"LOOT_CURRENCY","faction":"free_merchants","invert":false,"enabled":true,"is_vehicle":false,"is_personal":false,"cached_shift":[0,0,0],"start":[3981,3359,0],"end":[3981,3359,0]},{"name":"","type":"LOOT_WOOD","faction":"free_merchants","invert":false,"enabled":true,"is_vehicle":false,"is_personal":false,"cached_shift":[0,0,0],"start":[3982,3359,0],"end":[3982,3359,0]},{"name":"","type":"NPC_INVESTIGATE_ONLY","faction":"free_merchants","invert":false,"enabled":true,"is_vehicle":false,"is_personal":false,"cached_shift":[0,0,0],"start":[3960,3360,0],"end":[3983,3383,0]},{"name":"","type":"NPC_INVESTIGATE_ONLY","faction":"wasteland_scavengers","invert":false,"enabled":true,"is_vehicle":false,"is_personal":false,"cached_shift":[0,0,0],"start":[3960,3360,0],"end":[3983,3383,0]},{"name":"","type":"LOOT_UNSORTED","faction":"free_merchants","invert":false,"enabled":true,"is_vehicle":false,"is_personal":false,"cached_shift":[0,0,0],"start":[3983,3360,0],"end":[3983,3360,0]},{"name":"NPC Shopkeeper unsorted fallback zone","type":"LOOT_UNSORTED","faction":"no_faction","invert":false,"enabled":true,"is_vehicle":false,"is_personal":false,"cached_shift":[0,0,0],"start":[3963,3325,0],"end":[3965,3327,0]},{"name":"","type":"NPC_INVESTIGATE_ONLY","faction":"free_merchants","invert":false,"enabled":true,"is_vehicle":false,"is_personal":false,"cached_shift":[0,0,0],"start":[3984,3312,0],"end":[4007,3335,0]},{"name":"","type":"NPC_INVESTIGATE_ONLY","faction":"wasteland_scavengers","invert":false,"enabled":true,"is_vehicle":false,"is_personal":false,"cached_shift":[0,0,0],"start":[3984,3312,0],"end":[4007,3335,0]},{"name":"","type":"NPC_NO_INVESTIGATE","faction":"free_merchants","invert":false,"enabled":true,"is_vehicle":false,"is_personal":false,"cached_shift":[0,0,0],"start":[3987,3312,0],"end":[4004,3320,0]},{"name":"","type":"NPC_NO_INVESTIGATE","faction":"wasteland_scavengers","invert":false,"enabled":true,"is_vehicle":false,"is_personal":false,"cached_shift":[0,0,0],"start":[3987,3312,0],"end":[4004,3320,0]},{"name":"","type":"NPC_INVESTIGATE_ONLY","faction":"free_merchants","invert":false,"enabled":true,"is_vehicle":false,"is_personal":false,"cached_shift":[0,0,0],"start":[3984,3336,0],"end":[4007,3359,0]},{"name":"","type":"NPC_INVESTIGATE_ONLY","faction":"wasteland_scavengers","invert":false,"enabled":true,"is_vehicle":false,"is_personal":false,"cached_shift":[0,0,0],"start":[3984,3336,0],"end":[4007,3359,0]},{"name":"","type":"NPC_INVESTIGATE_ONLY","faction":"lobby_beggars","invert":false,"enabled":true,"is_vehicle":false,"is_personal":false,"cached_shift":[0,0,0],"start":[3984,3339,0],"end":[3986,3356,0]},{"name":"","type":"NPC_INVESTIGATE_ONLY","faction":"free_merchants","invert":false,"enabled":true,"is_vehicle":false,"is_personal":false,"cached_shift":[0,0,0],"start":[3984,3360,0],"end":[4007,3383,0]},{"name":"","type":"NPC_INVESTIGATE_ONLY","faction":"wasteland_scavengers","invert":false,"enabled":true,"is_vehicle":false,"is_personal":false,"cached_shift":[0,0,0],"start":[3984,3360,0],"end":[4007,3383,0]},{"name":"","type":"NPC_INVESTIGATE_ONLY","faction":"free_merchants","invert":false,"enabled":true,"is_vehicle":false,"is_personal":false,"cached_shift":[0,0,0],"start":[4008,3312,0],"end":[4031,3335,0]},{"name":"","type":"NPC_INVESTIGATE_ONLY","faction":"wasteland_scavengers","invert":false,"enabled":true,"is_vehicle":false,"is_personal":false,"cached_shift":[0,0,0],"start":[4008,3312,0],"end":[4031,3335,0]},{"name":"","type":"NPC_INVESTIGATE_ONLY","faction":"free_merchants","invert":false,"enabled":true,"is_vehicle":false,"is_personal":false,"cached_shift":[0,0,0],"start":[4008,3336,0],"end":[4031,3356,0]},{"name":"","type":"NPC_INVESTIGATE_ONLY","faction":"wasteland_scavengers","invert":false,"enabled":true,"is_vehicle":false,"is_personal":false,"cached_shift":[0,0,0],"start":[4008,3336,0],"end":[4031,3356,0]},{"name":"","type":"NPC_NO_INVESTIGATE","faction":"free_merchants","invert":false,"enabled":true,"is_vehicle":false,"is_personal":false,"cached_shift":[0,0,0],"start":[4008,3357,0],"end":[4029,3359,0]},{"name":"","type":"NPC_NO_INVESTIGATE","faction":"wasteland_scavengers","invert":false,"enabled":true,"is_vehicle":false,"is_personal":false,"cached_shift":[0,0,0],"start":[4008,3357,0],"end":[4029,3359,0]},{"name":"","type":"NPC_NO_INVESTIGATE","faction":"old_guard","invert":false,"enabled":true,"is_vehicle":false,"is_personal":false,"cached_shift":[0,0,0],"start":[4008,3357,0],"end":[4029,3359,0]},{"name":"","type":"NPC_NO_INVESTIGATE","faction":"lobby_beggars","invert":false,"enabled":true,"is_vehicle":false,"is_personal":false,"cached_shift":[0,0,0],"start":[4008,3357,0],"end":[4029,3359,0]},{"name":"","type":"NPC_NO_INVESTIGATE","faction":"free_merchants","invert":false,"enabled":true,"is_vehicle":false,"is_personal":false,"cached_shift":[0,0,0],"start":[4008,3360,0],"end":[4031,3383,0]},{"name":"","type":"NPC_NO_INVESTIGATE","faction":"wasteland_scavengers","invert":false,"enabled":true,"is_vehicle":false,"is_personal":false,"cached_shift":[0,0,0],"start":[4008,3360,0],"end":[4031,3383,0]},{"name":"","type":"NPC_NO_INVESTIGATE","faction":"old_guard","invert":false,"enabled":true,"is_vehicle":false,"is_personal":false,"cached_shift":[0,0,0],"start":[4008,3360,0],"end":[4031,3383,0]},{"name":"","type":"NPC_NO_INVESTIGATE","faction":"lobby_beggars","invert":false,"enabled":true,"is_vehicle":false,"is_personal":false,"cached_shift":[0,0,0],"start":[4008,3360,0],"end":[4031,3383,0]},{"name":"","type":"NPC_INVESTIGATE_ONLY","faction":"free_merchants","invert":false,"enabled":true,"is_vehicle":false,"is_personal":false,"cached_shift":[0,0,0],"start":[4032,3312,0],"end":[4032,3335,0]},{"name":"","type":"NPC_INVESTIGATE_ONLY","faction":"wasteland_scavengers","invert":false,"enabled":true,"is_vehicle":false,"is_personal":false,"cached_shift":[0,0,0],"start":[4032,3312,0],"end":[4032,3335,0]},{"name":"","type":"NPC_INVESTIGATE_ONLY","faction":"free_merchants","invert":false,"enabled":true,"is_vehicle":false,"is_personal":false,"cached_shift":[0,0,0],"start":[4032,3336,0],"end":[4032,3359,0]},{"name":"","type":"NPC_INVESTIGATE_ONLY","faction":"wasteland_scavengers","invert":false,"enabled":true,"is_vehicle":false,"is_personal":false,"cached_shift":[0,0,0],"start":[4032,3336,0],"end":[4032,3359,0]},{"name":"NPC Shopkeeper unsorted fallback zone","type":"LOOT_UNSORTED","faction":"robofac","invert":false,"enabled":true,"is_vehicle":false,"is_personal":false,"cached_shift":[0,0,0],"start":[3210,5242,0],"end":[3212,5244,0]}]